eagerx_pybullet/__init__.py
eagerx_pybullet/engine.py
eagerx_pybullet/enginenodes.py
eagerx_pybullet/enginestates.py
eagerx_pybullet/robot.py
eagerx_pybullet/world.py
eagerx_pybullet-0.1.11.dist-info/METADATA
eagerx_pybullet-0.1.11.dist-info/LICENSE
eagerx_pybullet-0.1.11.dist-info/WHEEL
eagerx_pybullet-0.1.11.dist-info/RECORD
