Metadata-Version: 2.1
Name: eagerx-pybullet
Version: 0.1.11
Summary: This repository contains the eagerx_pybllet package, which allows to simulate systems with EAGERx using pybullet.
Home-page: https://github.com/eager-dev/eagerx
License: Apache 2.0
Author: Bas van der Heijden
Author-email: d.s.vanderheijden@tudelft.nl
Requires-Python: >=3.6.2,<4.0.0
Classifier: License :: Other/Proprietary License
Classifier: Programming Language :: Python :: 3
Classifier: Programming Language :: Python :: 3.7
Classifier: Programming Language :: Python :: 3.8
Classifier: Programming Language :: Python :: 3.9
Classifier: Programming Language :: Python :: 3.10
Classifier: Programming Language :: Python :: 3.11
Requires-Dist: eagerx (>=0.1.32,<0.2.0)
Requires-Dist: pybullet (>=3.2.1,<4.0.0)
Project-URL: Documentation, https://eagerx.readthedocs.io/en/master/
Project-URL: Repository, https://github.com/eager-dev/eagerx_packages
